{
  "yPhWUmjbD_0": {
    "id": "yPhWUmjbD_0",
    "title": "Голубка (Deep House )",
    "channel": "MoD G - Topic",
    "views": 103001,
    "vpd": 11171,
    "days": 9.2,
    "url": "https://www.youtube.com/watch?v=yPhWUmjbD_0"
  },
  "KhWG4oAcuv0": {
    "id": "KhWG4oAcuv0",
    "title": "Rafs Perfume – Она танцует 🔥💃🔥 (Official Music Video)",
    "channel": "Rafs Perfume",
    "views": 290204,
    "vpd": 29237,
    "days": 9.9,
    "url": "https://www.youtube.com/watch?v=KhWG4oAcuv0"
  },
  "8ciaPishNP4": {
    "id": "8ciaPishNP4",
    "title": "Вольная дорога | Leons AISongs",
    "channel": "Leons AISongs",
    "views": 221324,
    "vpd": 41088,
    "days": 5.4,
    "url": "https://www.youtube.com/watch?v=8ciaPishNP4"
  },
  "qFkfYbnimQs": {
    "id": "qFkfYbnimQs",
    "title": "Какая женщина",
    "channel": "MR.VOV - Topic",
    "views": 138025,
    "vpd": 16461,
    "days": 8.4,
    "url": "https://www.youtube.com/watch?v=qFkfYbnimQs"
  },
  "sGIwvhPWtYo": {
    "id": "sGIwvhPWtYo",
    "title": "Я тебя…",
    "channel": "Марат Альборов - Topic",
    "views": 146390,
    "vpd": 16401,
    "days": 8.9,
    "url": "https://www.youtube.com/watch?v=sGIwvhPWtYo"
  },
  "CVxP97C4Yqk": {
    "id": "CVxP97C4Yqk",
    "title": "Без Тебя Не Могу",
    "channel": "VEXTIE - Topic",
    "views": 153360,
    "vpd": 18796,
    "days": 8.2,
    "url": "https://www.youtube.com/watch?v=CVxP97C4Yqk"
  },
  "Qg_gmrFK73E": {
    "id": "Qg_gmrFK73E",
    "title": "FIRIKH MUSIC — Ты Говоришь Что Я Пьян | Cover Remix | Trend Remix Viral 2026",
    "channel": "Firikh Music",
    "views": 203925,
    "vpd": 24808,
    "days": 8.2,
    "url": "https://www.youtube.com/watch?v=Qg_gmrFK73E"
  },
  "vebsHc8o15U": {
    "id": "vebsHc8o15U",
    "title": "Где тебя искать (Deep House)",
    "channel": "СТИМУЛ И - Topic",
    "views": 267808,
    "vpd": 35410,
    "days": 7.6,
    "url": "https://www.youtube.com/watch?v=vebsHc8o15U"
  },
  "R60AxKHcSAA": {
    "id": "R60AxKHcSAA",
    "title": "Девочка, Стоп! (Deep House )",
    "channel": "INGVAR - Topic",
    "views": 161921,
    "vpd": 24320,
    "days": 6.7,
    "url": "https://www.youtube.com/watch?v=R60AxKHcSAA"
  },
  "LG372BUPysU": {
    "id": "LG372BUPysU",
    "title": "Сеньорита (Deep House )",
    "channel": "Zyavo NEON - Topic",
    "views": 49734,
    "vpd": 5018,
    "days": 9.9,
    "url": "https://www.youtube.com/watch?v=LG372BUPysU"
  },
  "U4c8faGATsU": {
    "id": "U4c8faGATsU",
    "title": "Фара Ночи — Богиня моря🏖️🌊 (Новый клип 2026, Official Music Video) ",
    "channel": "Фара Ночи",
    "views": 103560,
    "vpd": 30226,
    "days": 3.4,
    "url": "https://www.youtube.com/watch?v=U4c8faGATsU"
  },
  "r1LRxn7a7PU": {
    "id": "r1LRxn7a7PU",
    "title": "Музыка 2026: хиты и трендовые ремиксы 🔥| Remix 2026 #хит #лучшиепесни #песни #remix #музыка",
    "channel": "NOIRA Music",
    "views": 67250,
    "vpd": 7001,
    "days": 9.6,
    "url": "https://www.youtube.com/watch?v=r1LRxn7a7PU"
  },
  "o-qIhWTXF88": {
    "id": "o-qIhWTXF88",
    "title": "Популярные песни: Самые Популярные Ремиксы 🔥🎧Remix+Covers 2026 #russianbesthits #carmusic #музыка",
    "channel": "Golden Rhythm Hub",
    "views": 26931,
    "vpd": 6984,
    "days": 3.9,
    "url": "https://www.youtube.com/watch?v=o-qIhWTXF88"
  },
  "-lwosxmkRkw": {
    "id": "-lwosxmkRkw",
    "title": "ХИТЫ 2026: хиты и трендовые ремиксы 🎧Remix+Covers 2026",
    "channel": "Golden Rhythm Hub",
    "views": 60309,
    "vpd": 21139,
    "days": 2.9,
    "url": "https://www.youtube.com/watch?v=-lwosxmkRkw"
  },
  "qmWbAMHQ8s4": {
    "id": "qmWbAMHQ8s4",
    "title": "Музыка 2026: хиты и трендовые ремиксы 🔥| Remix 2026 #хит #лучшиепесни #песни #remix #музыка",
    "channel": "NOIRA Music",
    "views": 12274,
    "vpd": 5161,
    "days": 2.4,
    "url": "https://www.youtube.com/watch?v=qmWbAMHQ8s4"
  },
  "NqMzRJw-PuU": {
    "id": "NqMzRJw-PuU",
    "title": "ХИТЫ 2026: хиты и трендовые ремиксы 🎧Remix+Covers 2026",
    "channel": "Golden Rhythm Hub",
    "views": 80233,
    "vpd": 16516,
    "days": 4.9,
    "url": "https://www.youtube.com/watch?v=NqMzRJw-PuU"
  },
  "3YUGK1_70uQ": {
    "id": "3YUGK1_70uQ",
    "title": "гимн россии на вк фест 2026 в санкт петербург #татьянакуртукова #музыка #топ",
    "channel": "makeeva fan",
    "views": 20212,
    "vpd": 5149,
    "days": 3.9,
    "url": "https://www.youtube.com/watch?v=3YUGK1_70uQ"
  },
  "nFEasgs6D4Y": {
    "id": "nFEasgs6D4Y",
    "title": "ПЕСНЯ ПРОСТО ОГОНЬ !🔥Премьера 2026",
    "channel": "Хрустальный Бит",
    "views": 53503,
    "vpd": 6629,
    "days": 8.1,
    "url": "https://www.youtube.com/watch?v=nFEasgs6D4Y"
  },
  "Epf4Va5p614": {
    "id": "Epf4Va5p614",
    "title": "Ты не мой, но я скучаю — Кавказский Deep House | Русская музыка 2026",
    "channel": "GoldenRUMusic ",
    "views": 58341,
    "vpd": 6133,
    "days": 9.5,
    "url": "https://www.youtube.com/watch?v=Epf4Va5p614"
  },
  "GPL1Rmzi2HQ": {
    "id": "GPL1Rmzi2HQ",
    "title": "Популярные песни: Самые Популярные Ремиксы 🔥🎧Remix+Covers 2026 #russianbesthits #carmusic #музыка",
    "channel": "Golden Rhythm Hub",
    "views": 10043,
    "vpd": 5127,
    "days": 2.0,
    "url": "https://www.youtube.com/watch?v=GPL1Rmzi2HQ"
  },
  "jPRA0otS0jw": {
    "id": "jPRA0otS0jw",
    "title": "ХИТЫ И РЕМИКСЫ 2026 🔥 Лучшие Песни 2026 | Новинки Музыки | Deep House & Remix Mix #music #песни ",
    "channel": "SOUND ZONE ",
    "views": 34346,
    "vpd": 5111,
    "days": 6.7,
    "url": "https://www.youtube.com/watch?v=jPRA0otS0jw"
  },
  "svABPMfs_1k": {
    "id": "svABPMfs_1k",
    "title": "Песня в исполнении Настасьи Самбурской раскрывает её как яркую и самобытную артистку😻🔥",
    "channel": "TheVs13 Music",
    "views": 56924,
    "vpd": 6206,
    "days": 9.2,
    "url": "https://www.youtube.com/watch?v=svABPMfs_1k"
  },
  "QS3nMj3BTsg": {
    "id": "QS3nMj3BTsg",
    "title": "Музыка 2026: хиты и трендовые ремиксы🔥🎧| Remix+Covers 2026 | Nicklaus Covers #музыка #popmusic #muz",
    "channel": "The Nicklaus",
    "views": 113232,
    "vpd": 11927,
    "days": 9.5,
    "url": "https://www.youtube.com/watch?v=QS3nMj3BTsg"
  },
  "bA7GgUF4g3E": {
    "id": "bA7GgUF4g3E",
    "title": "Одна из самых знаковых песен в их исполнении, которую они спели на юбилейном концерте Агутина😍🔥",
    "channel": "TheVs13 Music",
    "views": 162057,
    "vpd": 16680,
    "days": 9.7,
    "url": "https://www.youtube.com/watch?v=bA7GgUF4g3E"
  },
  "5qarRwXaVCM": {
    "id": "5qarRwXaVCM",
    "title": "Шадэ, Jony, Мальборо, Сомбреро, MiyaGi, MOT | ХИТЫ 2026 #всехиты2026 #хиты2026 #трендовыепесни #топ ",
    "channel": "◉ 022 | Studio ",
    "views": 114842,
    "vpd": 14876,
    "days": 7.7,
    "url": "https://www.youtube.com/watch?v=5qarRwXaVCM"
  },
  "ebXbBZAaOsE": {
    "id": "ebXbBZAaOsE",
    "title": "Лучшие хиты дискотеки в стиле 80-90-х Супер песни в одном видео #eurodisco #90sdancemusic #dance",
    "channel": "Грищук и Дуэт,, Гравитация,,",
    "views": 8609,
    "vpd": 5168,
    "days": 1.7,
    "url": "https://www.youtube.com/watch?v=ebXbBZAaOsE"
  },
  "ZaHGnMkbPtg": {
    "id": "ZaHGnMkbPtg",
    "title": "Petrosyan_s - ДОЛЯ",
    "channel": "Petrosyan - Topic",
    "views": 129034,
    "vpd": 23967,
    "days": 5.4,
    "url": "https://www.youtube.com/watch?v=ZaHGnMkbPtg"
  },
  "ZmeF0067z0Q": {
    "id": "ZmeF0067z0Q",
    "title": "Шадэ, Jony, Мальборо, Zivert, MiyaGi, MOT | ХИТЫ 2026 #всехиты2026 #хиты2026 #трендовыепесни #топ",
    "channel": "The Nicklaus",
    "views": 28836,
    "vpd": 16767,
    "days": 1.7,
    "url": "https://www.youtube.com/watch?v=ZmeF0067z0Q"
  },
  "2DXSrSdkH6E": {
    "id": "2DXSrSdkH6E",
    "title": "Dj017  О море море MV . Поет Роман Громов. Премьера клипа 2026",
    "channel": "ТВОРЧЕСКАЯ СТУДИЯ 17",
    "views": 145689,
    "vpd": 15732,
    "days": 9.3,
    "url": "https://www.youtube.com/watch?v=2DXSrSdkH6E"
  },
  "TESYGuFslSA": {
    "id": "TESYGuFslSA",
    "title": "Позвони! Я всё ещё жду",
    "channel": "Eduard Seibel - Topic",
    "views": 48226,
    "vpd": 7176,
    "days": 6.7,
    "url": "https://www.youtube.com/watch?v=TESYGuFslSA"
  }
}